LICENSE-2.0.txt
MANIFEST.in
README
_sunnytrail_urllib.py
http_serve.py
setup.py
sunnytrail
sunnytrail.py
test.py
sunnytrail.egg-info/PKG-INFO
sunnytrail.egg-info/SOURCES.txt
sunnytrail.egg-info/dependency_links.txt
sunnytrail.egg-info/top_level.txt