Metadata-Version: 1.0
Name: sunnytrail
Version: 0.1.1
Summary: Python Wrapper for the Sunnytrail API
Home-page: http://www.thesunnytrail.com/
Author: Sunnytrail Team
Author-email: andrei@thesunnytrail.com
License: UNKNOWN
Platform: UNKNOWN
Classifier: Development Status :: 4 - Beta
Classifier: Intended Audience :: Developers
Classifier: Programming Language :: Python
Classifier: License :: OSI Approved :: Apache Software License
Classifier: Operating System :: OS Independent
Classifier: Topic :: Software Development :: Libraries :: Python Modules
Classifier: Topic :: Utilities
